MANIFEST.in
README.rst
VERSION
requirements-install.txt
requirements-setup.txt
setup.py
src/news_extractor/__init__.py
src/news_extractor/exception.py
src/news_extractor/extractor.py
src/news_extractor/language_deal_title.py
src/news_extractor/log.py
src/news_extractor.egg-info/PKG-INFO
src/news_extractor.egg-info/SOURCES.txt
src/news_extractor.egg-info/dependency_links.txt
src/news_extractor.egg-info/requires.txt
src/news_extractor.egg-info/top_level.txt