Metadata-Version: 1.1
Name: news-extractor
Version: 0.9.2.dev0
Summary: web extrator
Home-page: UNKNOWN
Author: deng jian ping 
Author-email: 754335383@qq.com
License: MIT
Keywords: news_extractor
Platform: UNKNOWN
Classifier: Development Status :: 4 - Beta
Classifier: Intended Audience :: Developers
Classifier: License :: OSI Approved :: MIT License
Classifier: Natural Language :: English
Classifier: Programming Language :: Python :: 2
Classifier: Programming Language :: Python :: 2.7
Classifier: Programming Language :: Python :: 3
Classifier: Programming Language :: Python :: 3.4
Classifier: Programming Language :: Python :: 3.5
Classifier: Programming Language :: Python :: 3.6
